ensurepython/__init__.py
ensurepython/__main__.py
ensurepython/cli.py
ensurepython/py.typed
ensurepython-0.0.0.dist-info/LICENSE
ensurepython-0.0.0.dist-info/METADATA
ensurepython-0.0.0.dist-info/WHEEL
ensurepython-0.0.0.dist-info/entry_points.txt
ensurepython-0.0.0.dist-info/top_level.txt
ensurepython-0.0.0.dist-info/RECORD
